pyLaCroix/__init__.py
pyLaCroix/_pyLaCroix_module.py
pyLaCroix-0.0.11.dist-info/LICENSE
pyLaCroix-0.0.11.dist-info/METADATA
pyLaCroix-0.0.11.dist-info/WHEEL
pyLaCroix-0.0.11.dist-info/top_level.txt
pyLaCroix-0.0.11.dist-info/RECORD
