Metadata-Version: 2.1
Name: pyLaCroix
Version: 0.0.11
Summary: pyLaCroix - a python color palette for those that love sparkling water.
Home-page: https://github.com/mvinyard/pyLaCroix
Author: Michael E. Vinyard - Harvard University - Massachussetts General Hospital - Broad Institute of MIT and Harvard
Author-email: mvinyard@broadinstitute.org
License: MIT
Platform: UNKNOWN
Classifier: Development Status :: 2 - Pre-Alpha
Classifier: Programming Language :: Python :: 3.8
Classifier: Intended Audience :: Science/Research
Classifier: Topic :: Scientific/Engineering :: Bio-Informatics
Requires-Python: >3.8.0
License-File: LICENSE
Requires-Dist: colour
